fizz_cli/__init__.py
fizz_cli/main.py
fizz_cli/templates/__init__.py
fizz_cli/templates/main.py
fizz_cli/templates/route.yaml
fizz_cli/utils.py
fizz_cli-0.1.2.dist-info/entry_points.txt
fizz_cli-0.1.2.dist-info/METADATA
fizz_cli-0.1.2.dist-info/WHEEL
fizz_cli-0.1.2.dist-info/RECORD
