Metadata-Version: 2.1
Name: fizz-cli
Version: 0.1.2
Summary: 
Author: Kaustubh Kishore
Author-email: KaustubhKishorem@gmail.com
Requires-Python: >=3.10,<4.0
Classifier: Programming Language :: Python :: 3
Classifier: Programming Language :: Python :: 3.10
Classifier: Programming Language :: Python :: 3.11
Classifier: Programming Language :: Python :: 3.12
Requires-Dist: PyYAML (>=6.0.1,<7.0.0)
Requires-Dist: typer[all] (>=0.9.0,<0.10.0)
